{
    "$schema": "https://schema.management.azure.com/schemas/2015-01-01/deploymentParameters.json#",
    "contentVersion": "1.0.0.0",
    "parameters": {
        "storageAccountName": {
            "value": "garandsoftwarestaging"
        },
        "domainName": {
            "value": "garandsoftware.co.uk"
        },
        "domainPrefix": {
            "value": "staging"
        },
        "cdnProfileName": {
            "value": "garandsoftware-staging"
        },
        "cdnEndpointName": {
            "value": "garandsoftware-staging"
        }
    }
}